MANIFEST.in
VERSION
optional_requirements.txt
requirements.txt
setup.cfg
setup.py
bin/PrintGCStats
bin/addDateStampToGC
bin/naarad
bin/naarad_metric_collector.sh
lib/luminol/VERSION
lib/luminol/requirements.txt
lib/luminol/demo/requirements.txt
lib/luminol/demo/src/static/bootstrap.js
lib/luminol/demo/src/static/bootstrap.min.css
lib/luminol/demo/src/static/dygraph-combined.js
lib/luminol/demo/src/static/inversion.css
lib/luminol/demo/src/static/naarad.js
lib/luminol/demo/src/templates/index.html
src/naarad/__init__.py
src/naarad/httpdownload.py
src/naarad/naarad_constants.py
src/naarad/naarad_imports.py
src/naarad/sla.py
src/naarad/utils.py
src/naarad.egg-info/PKG-INFO
src/naarad.egg-info/SOURCES.txt
src/naarad.egg-info/dependency_links.txt
src/naarad.egg-info/pbr.json
src/naarad.egg-info/requires.txt
src/naarad.egg-info/top_level.txt
src/naarad/graphing/__init__.py
src/naarad/graphing/dygraphs.py
src/naarad/graphing/matplotlib_naarad.py
src/naarad/graphing/plot_data.py
src/naarad/graphing/pygal_naarad.py
src/naarad/metrics/__init__.py
src/naarad/metrics/cluster_metric.py
src/naarad/metrics/gc_metric.py
src/naarad/metrics/innotop_metric.py
src/naarad/metrics/jmeter_metric.py
src/naarad/metrics/linkedin_android_rum_metric.py
src/naarad/metrics/metric.py
src/naarad/metrics/netstat_metric.py
src/naarad/metrics/procinterrupts_metric.py
src/naarad/metrics/procmeminfo_metric.py
src/naarad/metrics/procvmstat_metric.py
src/naarad/metrics/proczoneinfo_metric.py
src/naarad/metrics/sar_metric.py
src/naarad/metrics/top_metric.py
src/naarad/reporting/__init__.py
src/naarad/reporting/diff.py
src/naarad/reporting/report.py
src/naarad/resources/__init__.py
src/naarad/resources/bootstrap.min.css
src/naarad/resources/bootstrap.min.js
src/naarad/resources/default_client_charting_page.html
src/naarad/resources/default_diff_client_charting_page.html
src/naarad/resources/default_diff_page.html
src/naarad/resources/default_metric_page.html
src/naarad/resources/default_report_footer.html
src/naarad/resources/default_report_header.html
src/naarad/resources/default_summary_content.html
src/naarad/resources/default_summary_page.html
src/naarad/resources/dygraph-combined.js
