Metadata-Version: 1.0
Name: naarad
Version: 1.0.16
Summary: Naarad is a Performance Analysis tool
Home-page: https://github.com/linkedin/naarad
Author: Naarad Developers
Author-email: naarad-dev@googlegroups.com
License: Apache 2.0
Platform: UNKNOWN
